{
  "channels": {
    "0": {
      "ant_comment": "phased array",
      "adc_sampling_frequency": 2.0,
      "adc_n_samples": 4800,
      "ant_orientation_phi": 0.0,
      "ant_orientation_theta": 0.0,
      "ant_position_x": 0.0,
      "ant_position_y": 20.0,
      "ant_position_z": -100.0,
      "ant_rotation_phi": 90.0,
      "ant_rotation_theta": 90.0,
      "ant_type": "RNOG_vpol_4inch_center_n1.73",
      "cab_time_delay": 0.0,
      "cab_type" : "LMR_400",
      "channel_id": 0,
      "station_id": 1,
      "noiseless" : false,
      "commission_time": "{TinyDate}:2017-11-01T00:00:00",
      "decommission_time": "{TinyDate}:2038-01-01T00:00:00"
    },
    "1": {
        "ant_comment": "phased array",
        "adc_sampling_frequency": 2.0,
        "adc_n_samples": 4800,
        "ant_orientation_phi": 0.0,
        "ant_orientation_theta": 0.0,
        "ant_position_x": 0.0,
        "ant_position_y": 20.0,
        "ant_position_z": -99.0,
        "ant_rotation_phi": 90.0,
        "ant_rotation_theta": 90.0,
        "ant_type": "RNOG_vpol_4inch_center_n1.73",
        "cab_time_delay": 0.0,
        "cab_type" : "LMR_400",
        "channel_id": 1,
        "station_id": 1,
        "noiseless" : false,
        "commission_time": "{TinyDate}:2017-11-01T00:00:00",
        "decommission_time": "{TinyDate}:2038-01-01T00:00:00"
    },
    "2": {
        "ant_comment": "phased array",
        "adc_sampling_frequency": 2.0,
        "adc_n_samples": 4800,
        "ant_orientation_phi": 0.0,
        "ant_orientation_theta": 0.0,
        "ant_position_x": 0.0,
        "ant_position_y": 20.0,
        "ant_position_z": -98.0,
        "ant_rotation_phi": 90.0,
        "ant_rotation_theta": 90.0,
        "ant_type": "RNOG_vpol_4inch_center_n1.73",
        "cab_time_delay": 0.0,
        "cab_type" : "LMR_400",
        "channel_id": 2,
        "station_id": 1,
        "noiseless" : false,
        "commission_time": "{TinyDate}:2017-11-01T00:00:00",
        "decommission_time": "{TinyDate}:2038-01-01T00:00:00"
    },
    "3": {
        "ant_comment": "phased array",
        "adc_sampling_frequency": 2.0,
        "adc_n_samples": 4800,
        "ant_orientation_phi": 0.0,
        "ant_orientation_theta": 0.0,
        "ant_position_x": 0.0,
        "ant_position_y": 20.0,
        "ant_position_z": -97.0,
        "ant_rotation_phi": 90.0,
        "ant_rotation_theta": 90.0,
        "ant_type": "RNOG_vpol_4inch_center_n1.73",
        "cab_time_delay": 0.0,
        "cab_type" : "LMR_400",
        "channel_id": 3,
        "station_id": 1,
        "noiseless" : false,
        "commission_time": "{TinyDate}:2017-11-01T00:00:00",
        "decommission_time": "{TinyDate}:2038-01-01T00:00:00"
    },
    "40": {
      "ant_comment": "phased array",
      "adc_sampling_frequency": 2.0,
      "adc_n_samples": 4800,
      "ant_orientation_phi": 0.0,
      "ant_orientation_theta": 0.0,
      "ant_position_x": 0.0,
      "ant_position_y": 20.0,
      "ant_position_z": -100.0,
      "ant_rotation_phi": 90.0,
      "ant_rotation_theta": 90.0,
      "ant_type": "RNOG_vpol_4inch_center_n1.73",
      "cab_time_delay": 0.0,
      "cab_type" : "LMR_400",
      "channel_id": 40,
      "station_id": 1,
      "noiseless" : true,
      "commission_time": "{TinyDate}:2017-11-01T00:00:00",
      "decommission_time": "{TinyDate}:2038-01-01T00:00:00"
    },
    "41": {
        "ant_comment": "phased array",
        "adc_sampling_frequency": 2.0,
        "adc_n_samples": 4800,
        "ant_orientation_phi": 0.0,
        "ant_orientation_theta": 0.0,
        "ant_position_x": 0.0,
        "ant_position_y": 20.0,
        "ant_position_z": -99.0,
        "ant_rotation_phi": 90.0,
        "ant_rotation_theta": 90.0,
        "ant_type": "RNOG_vpol_4inch_center_n1.73",
        "cab_time_delay": 0.0,
        "cab_type" : "LMR_400",
        "channel_id": 41,
        "station_id": 1,
        "noiseless" : true,
        "commission_time": "{TinyDate}:2017-11-01T00:00:00",
        "decommission_time": "{TinyDate}:2038-01-01T00:00:00"
    },
    "42": {
        "ant_comment": "phased array",
        "adc_sampling_frequency": 2.0,
        "adc_n_samples": 4800,
        "ant_orientation_phi": 0.0,
        "ant_orientation_theta": 0.0,
        "ant_position_x": 0.0,
        "ant_position_y": 20.0,
        "ant_position_z": -98.0,
        "ant_rotation_phi": 90.0,
        "ant_rotation_theta": 90.0,
        "ant_type": "RNOG_vpol_4inch_center_n1.73",
        "cab_time_delay": 0.0,
        "cab_type" : "LMR_400",
        "channel_id": 42,
        "station_id": 1,
        "noiseless" : true,
        "commission_time": "{TinyDate}:2017-11-01T00:00:00",
        "decommission_time": "{TinyDate}:2038-01-01T00:00:00"
    },
    "43": {
        "ant_comment": "phased array",
        "adc_sampling_frequency": 2.0,
        "adc_n_samples": 4800,
        "ant_orientation_phi": 0.0,
        "ant_orientation_theta": 0.0,
        "ant_position_x": 0.0,
        "ant_position_y": 20.0,
        "ant_position_z": -97.0,
        "ant_rotation_phi": 90.0,
        "ant_rotation_theta": 90.0,
        "ant_type": "RNOG_vpol_4inch_center_n1.73",
        "cab_time_delay": 0.0,
        "cab_type" : "LMR_400",
        "channel_id": 43,
        "station_id": 1,
        "noiseless" : true,
        "commission_time": "{TinyDate}:2017-11-01T00:00:00",
        "decommission_time": "{TinyDate}:2038-01-01T00:00:00"
    }
  },
  "stations": {
    "01": {
      "pos_altitude": 0.0,
      "pos_easting": 0.0,
      "pos_northing": 0.0,
      "pos_site": "summit",
      "station_id": 1,
      "station_type": null,
      "commission_time": "{TinyDate}:2017-11-04T00:00:00",
      "decommission_time": "{TinyDate}:2038-01-01T00:00:00"
    }
  }
}
